{"camFollow":[800,360],"pieces":[{"asset":"limoSunset","scrollFactor":[0.1,0.1],"position":[-120,-50],"layer":0,"antialias":true,"type":"static","id":""},{"asset":"bgLimo","position":[-200,480],"layer":0,"type":"animated","id":"","scrollFactor":[0.4,0.4],"firstAnimation":"drive","antialias":true,"animations":[{"prefix":"background limo pink","loop":true,"name":"drive","fps":24}]},{"asset":"limoDancer","position":[130,490],"layer":0,"type":"animated","id":"dumb0","firstAnimation":"danceLeft","scrollFactor":[0.4,0.4],"align":"bottomleft","antialias":true,"animations":[{"indices":[-1,0,14],"prefix":"bg dancer sketch PINK","fps":24,"loop":false,"name":"danceLeft"},{"indices":[-1,15,29],"prefix":"bg dancer sketch PINK","fps":24,"loop":false,"name":"danceRight"}],"idles":["danceLeft","danceRight"]},{"asset":"limoDancer","position":[500,490],"layer":0,"type":"animated","id":"dumb1","firstAnimation":"danceLeft","scrollFactor":[0.4,0.4],"align":"bottomleft","antialias":true,"animations":[{"indices":[-1,0,14],"prefix":"bg dancer sketch PINK","fps":24,"loop":false,"name":"danceLeft"},{"indices":[-1,15,29],"prefix":"bg dancer sketch PINK","fps":24,"loop":false,"name":"danceRight"}],"idles":["danceLeft","danceRight"]},{"asset":"limoDancer","position":[870,490],"layer":0,"type":"animated","id":"dumb2","firstAnimation":"danceLeft","scrollFactor":[0.4,0.4],"align":"bottomleft","antialias":true,"animations":[{"indices":[-1,0,14],"prefix":"bg dancer sketch PINK","fps":24,"loop":false,"name":"danceLeft"},{"indices":[-1,15,29],"prefix":"bg dancer sketch PINK","fps":24,"loop":false,"name":"danceRight"}],"idles":["danceLeft","danceRight"]},{"asset":"limoDancer","position":[1240,490],"layer":0,"type":"animated","id":"dumb3","firstAnimation":"danceLeft","scrollFactor":[0.4,0.4],"align":"bottomleft","antialias":true,"animations":[{"indices":[-1,0,14],"prefix":"bg dancer sketch PINK","fps":24,"loop":false,"name":"danceLeft"},{"indices":[-1,15,29],"prefix":"bg dancer sketch PINK","fps":24,"loop":false,"name":"danceRight"}],"idles":["danceLeft","danceRight"]},{"asset":"fastCarLol","scriptClass":"LimoCar","position":[-12600,160],"layer":0,"type":"static","antialias":true,"id":""},{"asset":"limoDrive","firstAnimation":"drive","position":[-120,550],"layer":1,"type":"animated","antialias":true,"id":"","animations":[{"prefix":"Limo stage","loop":true,"name":"drive","fps":24}]}],"camZoom":0.9,"characters":[{"camPosition":[-200,0],"position":[1030,-120],"flip":true},{"position":[100,100],"flip":false},{"scrollFactor":[0.95,0.95],"position":[400,130],"flip":false}]}