{
	"parameters":
	[
		{
			"id": "r",
			"label": "Color",
			"infoText": "The color the subtitle text should be.",
			"type": "color",
			"defaultValue": 255
		},
		{
			"id": "g",
			"label": "",
			"type": "invis",
			"defaultValue": 255
		},
		{
			"id": "b",
			"label": "",
			"type": "invis",
			"defaultValue": 255
		},
		{
			"id": "font",
			"label": "Font",
			"infoText": "The font to use for the subtitle text.",
			"type": "string",
			"defaultValue": ""
		},
		{
			"id": "size",
			"label": "Size",
			"infoText": "The font size of the subtitle text.",
			"type": "stepper",
			"defaultValue": 0,
			"min": 0,
			"max": 9999,
			"increment": 1,
			"decimals": 0
		},
		{
			"id": "width",
			"label": "Width",
			"infoText": "The maximum width the subtitles are allowed to be before word wrapping.",
			"type": "stepper",
			"defaultValue": 0,
			"min": 0,
			"max": 1280,
			"increment": 1,
			"decimals": 0
		},
		{
			"type": "label",
			"label": "All settings except color can be reset to default by either setting them to 0 or leaving them blank"
		}
	]
}